devops_microsoft_sspo_etl/__init__.py
devops_microsoft_sspo_etl/base_entity.py
devops_microsoft_sspo_etl/factories.py
devops_microsoft_sspo_etl/product_backlog.py
devops_microsoft_sspo_etl/scrum_development_task.py
devops_microsoft_sspo_etl/scrum_project.py
devops_microsoft_sspo_etl/scrum_project_team.py
devops_microsoft_sspo_etl/sprint.py
devops_microsoft_sspo_etl/team_member.py
devops_microsoft_sspo_etl/user_story.py
devops_microsoft_sspo_etl/user_story_abastract.py
devops_microsoft_sspo_etl-4.0.1.dist-info/METADATA
devops_microsoft_sspo_etl-4.0.1.dist-info/WHEEL
devops_microsoft_sspo_etl-4.0.1.dist-info/top_level.txt
devops_microsoft_sspo_etl-4.0.1.dist-info/RECORD
