Metadata-Version: 2.1
Name: devops-microsoft-sspo-etl
Version: 4.0.1
Summary: xxxx
Home-page: UNKNOWN
Author: Paulo Sergio dos Santo Junior
Author-email: paulossjuniort@gmail.com
License: UNKNOWN
Platform: UNKNOWN
Classifier: Programming Language :: Python :: 3
Classifier: License :: OSI Approved :: MIT License
Classifier: Operating System :: OS Independent
Requires-Dist: sspo-db
Requires-Dist: tfsx
Requires-Dist: devops-microsoft-mapping-sspo
